vibe_surf/__init__.py
vibe_surf/_version.py
vibe_surf/cli.py
vibe_surf/common.py
vibe_surf/logger.py
vibe_surf/utils.py
vibe_surf/agents/__init__.py
vibe_surf/agents/browser_use_agent.py
vibe_surf/agents/report_writer_agent.py
vibe_surf/agents/vibe_surf_agent.py
vibe_surf/agents/views.py
vibe_surf/agents/prompts/__init__.py
vibe_surf/agents/prompts/report_writer_prompt.py
vibe_surf/agents/prompts/vibe_surf_prompt.py
vibe_surf/backend/__init__.py
vibe_surf/backend/llm_config.py
vibe_surf/backend/main.py
vibe_surf/backend/shared_state.py
vibe_surf/backend/voice_model_config.py
vibe_surf/backend/api/__init__.py
vibe_surf/backend/api/activity.py
vibe_surf/backend/api/agent.py
vibe_surf/backend/api/browser.py
vibe_surf/backend/api/composio.py
vibe_surf/backend/api/config.py
vibe_surf/backend/api/files.py
vibe_surf/backend/api/models.py
vibe_surf/backend/api/task.py
vibe_surf/backend/api/voices.py
vibe_surf/backend/database/__init__.py
vibe_surf/backend/database/manager.py
vibe_surf/backend/database/models.py
vibe_surf/backend/database/queries.py
vibe_surf/backend/database/schemas.py
vibe_surf/backend/database/migrations/v001_initial_schema.sql
vibe_surf/backend/database/migrations/v002_add_agent_mode.sql
vibe_surf/backend/database/migrations/v003_fix_task_status_case.sql
vibe_surf/backend/database/migrations/v004_add_voice_profiles.sql
vibe_surf/backend/database/migrations/v005_add_composio_integration.sql
vibe_surf/backend/database/migrations/v006_add_credentials_table.sql
vibe_surf/backend/utils/__init__.py
vibe_surf/backend/utils/encryption.py
vibe_surf/backend/utils/llm_factory.py
vibe_surf/backend/utils/utils.py
vibe_surf/browser/__init__.py
vibe_surf/browser/agen_browser_profile.py
vibe_surf/browser/agent_browser_session.py
vibe_surf/browser/browser_manager.py
vibe_surf/browser/utils.py
vibe_surf/browser/watchdogs/__init__.py
vibe_surf/browser/watchdogs/action_watchdog.py
vibe_surf/browser/watchdogs/dom_watchdog.py
vibe_surf/chrome_extension/background.js
vibesurf-0.1.43.dist-info/licenses/LICENSE
vibesurf-0.1.43.dist-info/METADATA
vibesurf-0.1.43.dist-info/WHEEL
vibesurf-0.1.43.dist-info/entry_points.txt
vibesurf-0.1.43.dist-info/top_level.txt
vibesurf-0.1.43.dist-info/RECORD
