Metadata-Version: 2.4
Name: vibesurf
Version: 0.1.43
Summary: VibeSurf: A powerful browser assistant for vibe surfing
Author: WarmShao
License: Apache-2.0
Project-URL: Repository, https://github.com/vibesurf-ai/VibeSurf
Keywords: browser use,browser automation,browser assistant,agentic browser,vibe surf,AI browser
Classifier: Development Status :: 3 - Alpha
Classifier: Intended Audience :: Developers
Classifier: License :: OSI Approved :: Apache Software License
Classifier: Operating System :: OS Independent
Classifier: Programming Language :: Python :: 3
Classifier: Topic :: Software Development :: Libraries :: Python Modules
Classifier: Topic :: Internet :: WWW/HTTP :: Browsers
Requires-Python: >=3.11
License-File: LICENSE
Requires-Dist: uuid7>=0.1.0
Requires-Dist: aiofiles>=24.1.0
Requires-Dist: anyio>=4.9.0
Requires-Dist: psutil>=7.0.0
Requires-Dist: pydantic>=2.11.5
Requires-Dist: cdp-use>=1.4.1
Requires-Dist: json-repair>=0.48.0
Requires-Dist: aiohttp>=3.12.15
Requires-Dist: scikit-image>=0.25.2
Requires-Dist: python-socks>=2.7.2
Requires-Dist: langgraph>=0.6.4
Requires-Dist: fastapi>=0.104.0
Requires-Dist: uvicorn[standard]>=0.24.0
Requires-Dist: python-multipart>=0.0.6
Requires-Dist: websockets>=12.0
Requires-Dist: python-dotenv>=1.0.0
Requires-Dist: sqlalchemy>=2.0.43
Requires-Dist: aiosqlite>=0.21.0
Requires-Dist: rich>=13.0.0
Requires-Dist: greenlet>=3.2.4
Requires-Dist: getmac>=0.9.5
Requires-Dist: markdown-pdf>=1.9
Requires-Dist: nanoid>=2.0.0
Requires-Dist: markdownify>=1.2.0
Requires-Dist: pathvalidate>=3.3.1
Requires-Dist: dashscope>=1.24.5
Requires-Dist: yfinance>=0.2.66
Requires-Dist: pyexecjs>=1.5.1
Requires-Dist: youtube-transcript-api>=1.2.2
Requires-Dist: composio>=0.8.20
Requires-Dist: composio-langchain>=0.8.20
Requires-Dist: browser-use==0.8.1
Requires-Dist: google-genai<2.0.0,>=1.29.0
Requires-Dist: openai<2.0.0,>=1.99.2
Requires-Dist: google-api-python-client>=2.174.0
Requires-Dist: google-auth>=2.40.3
Requires-Dist: google-auth-oauthlib>=1.2.2
Dynamic: license-file
